textual_advanced_google_search/__about__.py
textual_advanced_google_search/__init__.py
textual_advanced_google_search/entry_points.py
textual_advanced_google_search/ganglion.toml
textual_advanced_google_search/ganglionMain.py
textual_advanced_google_search/nohup.out
textual_advanced_google_search/search.py
textual_advanced_google_search-0.0.3.dist-info/METADATA
textual_advanced_google_search-0.0.3.dist-info/WHEEL
textual_advanced_google_search-0.0.3.dist-info/entry_points.txt
textual_advanced_google_search-0.0.3.dist-info/licenses/LICENSE.txt
textual_advanced_google_search-0.0.3.dist-info/RECORD
