Metadata-Version: 2.3
Name: textual-advanced-google-search
Version: 0.0.3
Summary: Second level google search
Author-email: Prakhar Gandhi <gprakhar0@gmail.com>
License-Expression: MIT
License-File: LICENSE.txt
Classifier: Development Status :: 4 - Beta
Classifier: Programming Language :: Python
Classifier: Programming Language :: Python :: 3.8
Classifier: Programming Language :: Python :: 3.9
Classifier: Programming Language :: Python :: 3.10
Classifier: Programming Language :: Python :: 3.11
Classifier: Programming Language :: Python :: 3.12
Classifier: Programming Language :: Python :: Implementation :: CPython
Classifier: Programming Language :: Python :: Implementation :: PyPy
Requires-Python: >=3.8
Requires-Dist: emotionextractor
Requires-Dist: googletrans==4.0.0-rc1
Requires-Dist: lingua-language-detector
Requires-Dist: ml-things
Requires-Dist: mpire
Requires-Dist: playwright
Requires-Dist: shutup
Requires-Dist: textual
